data/chunks/chem.204703_1_5.0167542.json
data/chunks/chem.bassani-et-al-2024-nanocrystal-assemblies-current-advances-and-open-problems.json
data/chunks/clinical.trials.NCT01239745.json
data/chunks/clinical.trials.NCT04896073.json
data/chunks/fin.10Q.apple.json
data/chunks/fin.10Q.nvidia.json
data/chunks/fin.10Q.sfix.json
data/chunks/random.json
data/json/chem.204703_1_5.0167542.json
data/json/chem.bassani-et-al-2024-nanocrystal-assemblies-current-advances-and-open-problems.json
data/json/clinical.trials.NCT01239745.json
data/json/clinical.trials.NCT04896073.json
data/json/fin.10Q.apple.json
data/json/fin.10Q.nvidia.json
data/json/fin.10Q.sfix.json
data/json/random.json
data/ontologies/criminal.ttl
data/ontologies/fin-securities.ttl
data/pdf/chem.204703_1_5.0167542.pdf
data/pdf/chem.bassani-et-al-2024-nanocrystal-assemblies-current-advances-and-open-problems.pdf
data/pdf/fin.10Q.apple.pdf
data/pdf/fin.10Q.nvidia.pdf
data/pdf/fin.10Q.sfix.pdf
data/test/json/fin.10Q.apple.json
ontocast/__init__.py
ontocast/config.py
ontocast/toolbox.py
ontocast/util.py
ontocast/agent/__init__.py
ontocast/agent/aggregate_serialize.py
ontocast/agent/check_chunks.py
ontocast/agent/chunk_text.py
ontocast/agent/common.py
ontocast/agent/convert_document.py
ontocast/agent/criticise_facts.py
ontocast/agent/criticise_ontology.py
ontocast/agent/render_facts.py
ontocast/agent/render_ontology.py
ontocast/agent/select_ontology.py
ontocast/agent/sublimate_ontology.py
ontocast/cli/__init__.py
ontocast/cli/batch_process.py
ontocast/cli/cmp_states.py
ontocast/cli/merge_ontologies.py
ontocast/cli/pdfs_to_markdown.py
ontocast/cli/plot_graph.py
ontocast/cli/serve.py
ontocast/cli/split_chunks.py
ontocast/cli/test_api.py
ontocast/cli/util.py
ontocast/onto/__init__.py
ontocast/onto/chunk.py
ontocast/onto/constants.py
ontocast/onto/context.py
ontocast/onto/enum.py
ontocast/onto/model.py
ontocast/onto/null.py
ontocast/onto/ontology.py
ontocast/onto/ontology_operations.py
ontocast/onto/rdfgraph.py
ontocast-0.2.4.dist-info/METADATA
ontocast-0.2.4.dist-info/WHEEL
ontocast-0.2.4.dist-info/entry_points.txt
ontocast-0.2.4.dist-info/licenses/LICENSE
ontocast-0.2.4.dist-info/RECORD
