Metadata-Version: 2.4
Name: ontocast
Version: 0.2.4
Summary: Agentic ontology and knowledge graph co-generation
License-File: LICENSE
Requires-Python: >=3.12
Requires-Dist: asyncio>=3.4.3
Requires-Dist: click>=8.1.8
Requires-Dist: httpx>=0.27.0
Requires-Dist: langchain-core>=0.3.60
Requires-Dist: langchain-experimental>=0.3.4
Requires-Dist: langchain-huggingface>=0.2.0
Requires-Dist: langchain-ollama>=0.3.3
Requires-Dist: langchain-openai>=0.3.17
Requires-Dist: langchain>=0.3.25
Requires-Dist: langgraph>=0.2.35
Requires-Dist: neo4j>=5.28.1
Requires-Dist: networkx>=3.0
Requires-Dist: owlready2>=0.47
Requires-Dist: pydantic>=2.11.9
Requires-Dist: pyld>=2.0.4
Requires-Dist: rapidfuzz>=3.13.0
Requires-Dist: rdflib>=7.1.4
Requires-Dist: rich>=14.0.0
Requires-Dist: robyn>=0.66.2
Requires-Dist: simsimd>=6.2.1
Requires-Dist: suthing>=0.4.1
